<?xml version='1.0' encoding='utf-8'?>
<odoo>
        <data>
            <record id="view_school_form_quality" model="ir.ui.view">
            <field name="name">ix.school.inherit.quality.view.form</field>
            <field name="model">ix.school</field>
            <field name="inherit_id" ref="ixcatalog.view_school_form_catalog"/>
            <field name="arch" type="xml">
                <xpath expr="//field[@name='level']" position="after">
                    <field name="accreditation_ids" widget="many2many_tags"/>
                </xpath>
            </field>
        </record>
        </data>
</odoo>